napari_netpbmfile/__init__.py
napari_netpbmfile-0.0.3.dist-info/METADATA
napari_netpbmfile-0.0.3.dist-info/WHEEL
napari_netpbmfile-0.0.3.dist-info/entry_points.txt
napari_netpbmfile-0.0.3.dist-info/top_level.txt
napari_netpbmfile-0.0.3.dist-info/RECORD
