Metadata-Version: 2.1
Name: napari-netpbmfile
Version: 0.0.3
Summary: A napari plugin for reading files via netpbmfile
Home-page: https://www.lfd.uci.edu/~gohlke/
Author: Christoph Gohlke
Author-email: cgohlke@uci.edu
License: BSD
Project-URL: Bug Tracker, https://github.com/cgohlke/netpbmfile/issues
Project-URL: Source Code, https://github.com/cgohlke/netpbmfile
Platform: any
Classifier: Development Status :: 3 - Alpha
Classifier: License :: OSI Approved :: BSD License
Classifier: Intended Audience :: Science/Research
Classifier: Operating System :: OS Independent
Classifier: Programming Language :: Python :: 3 :: Only
Classifier: Programming Language :: Python :: 3.8
Classifier: Programming Language :: Python :: 3.9
Classifier: Programming Language :: Python :: 3.10
Requires-Python: >=3.8
Requires-Dist: netpbmfile
